README.md
setup.cfg
setup.py
wrench/__init__.py
wrench/compute_service.py
wrench/exception.py
wrench/simulation.py
wrench/simulation_item.py
wrench/standard_job.py
wrench/storage_service.py
wrench/task.py
wrench/version.py
wrench_api.egg-info/PKG-INFO
wrench_api.egg-info/SOURCES.txt
wrench_api.egg-info/dependency_links.txt
wrench_api.egg-info/requires.txt
wrench_api.egg-info/top_level.txt