Metadata-Version: 2.1
Name: wrench-api
Version: 0.1
Summary: A Python API for the WRENCH simulation framework
Home-page: https://github.com/wrench-project/wrench-python-api
Author: WRENCH team
Author-email: support@wrench-project.org
License: GPLv3
Platform: UNKNOWN
Classifier: License :: OSI Approved :: GNU General Public License v3 (GPLv3)
Classifier: Operating System :: OS Independent
Classifier: Programming Language :: Python :: 3
Classifier: Programming Language :: Python :: 3.6
Classifier: Programming Language :: Python :: 3.7
Classifier: Programming Language :: Python :: 3.8
Classifier: Programming Language :: Python :: 3.9
Classifier: Intended Audience :: Developers
Classifier: Intended Audience :: Education
Classifier: Intended Audience :: Science/Research
Classifier: Natural Language :: English
Classifier: Topic :: Documentation :: Sphinx
Classifier: Topic :: System :: Distributed Computing
Requires-Python: >=3.6
